setup.py
distributions/Binomialdistribution.py
distributions/Gaussiandistribution.py
distributions/Generaldistribution.py
distributions/__init__.py
gbinom_dist.egg-info/PKG-INFO
gbinom_dist.egg-info/SOURCES.txt
gbinom_dist.egg-info/dependency_links.txt
gbinom_dist.egg-info/not-zip-safe
gbinom_dist.egg-info/top_level.txt