Metadata-Version: 1.0
Name: gbinom-dist
Version: 0.1
Summary: Gaussian distributions
Home-page: UNKNOWN
Author: UNKNOWN
Author-email: mihirsanchaniya@yahoo.com
License: UNKNOWN
Platform: UNKNOWN
